odin_ope/__init__.py
odin_ope/bundle.py
odin_ope/cid.py
odin_ope/cli.py
odin_ope/constants.py
odin_ope/envelope.py
odin_ope/exceptions.py
odin_ope/models.py
odin_ope/py.typed
odin_ope/signers.py
odin_ope/utils.py
odin_ope/verify.py
odin_ope-0.9.0.dist-info/licenses/LICENSE
odin_ope-0.9.0.dist-info/METADATA
odin_ope-0.9.0.dist-info/WHEEL
odin_ope-0.9.0.dist-info/entry_points.txt
odin_ope-0.9.0.dist-info/top_level.txt
odin_ope-0.9.0.dist-info/RECORD
