Metadata-Version: 2.4
Name: odin-ope
Version: 0.9.0
Summary: ODIN Open Proof Envelope (OPE): canonical JSON, CID hashing, Ed25519 signatures, verifiable envelopes & bundles
Author-email: ODIN Protocol <maintainers@odinprotocol.dev>
License-Expression: Apache-2.0
Project-URL: Homepage, https://github.com/odin-protocol/odin-ope
Project-URL: Documentation, https://github.com/odin-protocol/odin-ope#readme
Project-URL: Source, https://github.com/odin-protocol/odin-ope
Project-URL: Changelog, https://github.com/odin-protocol/odin-ope/releases
Project-URL: Issues, https://github.com/odin-protocol/odin-ope/issues
Keywords: odin,ope,provenance,envelope,ed25519,cid,signature,audit,ai,security
Classifier: Programming Language :: Python :: 3
Classifier: Programming Language :: Python :: 3 :: Only
Classifier: Programming Language :: Python :: 3.10
Classifier: Programming Language :: Python :: 3.11
Classifier: Programming Language :: Python :: 3.12
Classifier: Topic :: Security :: Cryptography
Classifier: Typing :: Typed
Requires-Python: >=3.10
License-File: LICENSE
Requires-Dist: cryptography>=43.0.1
Provides-Extra: gcpkms
Requires-Dist: google-cloud-kms>=2.24.0; extra == "gcpkms"
Provides-Extra: awskms
Requires-Dist: boto3>=1.34.0; extra == "awskms"
Provides-Extra: azurekv
Requires-Dist: azure-identity>=1.16.0; extra == "azurekv"
Requires-Dist: azure-keyvault-keys>=4.9.0; extra == "azurekv"
Provides-Extra: dev
Requires-Dist: mypy>=1.11.0; extra == "dev"
Requires-Dist: pytest; extra == "dev"
Requires-Dist: pytest-cov; extra == "dev"
Requires-Dist: hypothesis; extra == "dev"
Requires-Dist: black>=24.4.0; extra == "dev"
Requires-Dist: ruff>=0.5.0; extra == "dev"
Requires-Dist: pre-commit>=3.7.0; extra == "dev"
Dynamic: license-file
